eth_abi_tool/__init__.py
eth_abi_tool/abi.py
eth_abi_tool/cli.py
eth_abi_tool/exception_handler.py
eth_abi_tool/main.py
eth_abi_tool/version.py
eth_abi_tool-0.3.8.dist-info/entry_points.txt
eth_abi_tool-0.3.8.dist-info/LICENSE
eth_abi_tool-0.3.8.dist-info/WHEEL
eth_abi_tool-0.3.8.dist-info/METADATA
eth_abi_tool-0.3.8.dist-info/RECORD
