Metadata-Version: 2.1
Name: eth-abi-tool
Version: 0.3.8
Summary: Top-level package for eth-abi-tool.
Keywords: eth_abi_tool
Author-email: Matt Krueger <mkrueger@rstms.net>
Classifier: Intended Audience :: Developers
Classifier: Natural Language :: English
Classifier: Programming Language :: Python :: 3
Classifier: Programming Language :: Python :: 3.10
Requires-Dist: click
Requires-Dist: eth-hash[pycryptodome]
Requires-Dist: eth-utils
Requires-Dist: python-box
Requires-Dist: ratelimiter
Requires-Dist: requests
Requires-Dist: tablib[cli,yaml]
Requires-Dist: black ; extra == "dev"
Requires-Dist: bump2version ; extra == "dev"
Requires-Dist: coverage ; extra == "dev"
Requires-Dist: isort ; extra == "dev"
Requires-Dist: flake8 ; extra == "dev"
Requires-Dist: flake8-length ; extra == "dev"
Requires-Dist: pytest ; extra == "dev"
Requires-Dist: python-box ; extra == "dev"
Requires-Dist: toml ; extra == "dev"
Requires-Dist: tox ; extra == "dev"
Requires-Dist: m2r2 ; extra == "docs"
Requires-Dist: sphinx ; extra == "docs"
Requires-Dist: sphinx-click ; extra == "docs"
Requires-Dist: sphinx-rtd-theme ; extra == "docs"
Project-URL: Home, https://github.com/rstms/eth_abi_tool
Provides-Extra: dev
Provides-Extra: docs
